lins_plugboleto/__init__.py
lins_plugboleto/authorize.py
lins_plugboleto/criar_boleto.py
lins_plugboleto/environment.py
lins_plugboleto/objectJSON.py
lins_plugboleto/plugBoleto.py
lins_plugboleto/request/__init__.py
lins_plugboleto/request/baixar_boleto.py
lins_plugboleto/request/base.py
lins_plugboleto/request/busca_boleto.py
lins_plugboleto/request/criar_boleto.py
lins_plugboleto/request/numero_doc.py
tests/__init__.py
tests/mocks.py
tests/testar_criacao_boleto.py
tests/utils.py
lins_plugboleto-1.1.0.102.dist-info/METADATA
lins_plugboleto-1.1.0.102.dist-info/WHEEL
lins_plugboleto-1.1.0.102.dist-info/top_level.txt
lins_plugboleto-1.1.0.102.dist-info/RECORD
