Metadata-Version: 2.1
Name: lins-plugboleto
Version: 1.1.0.102
Summary: Pacote de consumo da Plug Boleto
Home-page: https://bitbucket.org/grupolinsferrao/pypck-lins-plugboleto/
Author: grupo lins ferrao
Author-email: ti.sistemas@grupolinsferrao.com.br
License: MIT
Platform: UNKNOWN
